airflow/sdk/__init__.py
airflow/sdk/__init__.pyi
airflow/sdk/exceptions.py
airflow/sdk/log.py
airflow/sdk/module_loading.py
airflow/sdk/py.typed
airflow/sdk/timezone.py
airflow/sdk/types.py
airflow/sdk/_shared/logging/__init__.py
airflow/sdk/_shared/logging/_config.py
airflow/sdk/_shared/logging/_noncaching.py
airflow/sdk/_shared/logging/percent_formatter.py
airflow/sdk/_shared/logging/structlog.py
airflow/sdk/_shared/logging/types.py
airflow/sdk/_shared/secrets_masker/__init__.py
airflow/sdk/_shared/secrets_masker/secrets_masker.py
airflow/sdk/_shared/timezones/__init__.py
airflow/sdk/_shared/timezones/timezone.py
airflow/sdk/api/__init__.py
airflow/sdk/api/client.py
airflow/sdk/api/datamodels/__init__.py
airflow/sdk/api/datamodels/_generated.py
airflow/sdk/api/datamodels/activities.py
airflow/sdk/bases/__init__.py
airflow/sdk/bases/decorator.py
airflow/sdk/bases/hook.py
airflow/sdk/bases/notifier.py
airflow/sdk/bases/operator.py
airflow/sdk/bases/operatorlink.py
airflow/sdk/bases/sensor.py
airflow/sdk/bases/xcom.py
airflow/sdk/definitions/__init__.py
airflow/sdk/definitions/connection.py
airflow/sdk/definitions/context.py
airflow/sdk/definitions/dag.py
airflow/sdk/definitions/deadline.py
airflow/sdk/definitions/edges.py
airflow/sdk/definitions/mappedoperator.py
airflow/sdk/definitions/operator_resources.py
airflow/sdk/definitions/param.py
airflow/sdk/definitions/taskgroup.py
airflow/sdk/definitions/template.py
airflow/sdk/definitions/variable.py
airflow/sdk/definitions/xcom_arg.py
airflow/sdk/definitions/_internal/__init__.py
airflow/sdk/definitions/_internal/abstractoperator.py
airflow/sdk/definitions/_internal/contextmanager.py
airflow/sdk/definitions/_internal/dag_parsing_context.py
airflow/sdk/definitions/_internal/decorators.py
airflow/sdk/definitions/_internal/expandinput.py
airflow/sdk/definitions/_internal/mixins.py
airflow/sdk/definitions/_internal/node.py
airflow/sdk/definitions/_internal/setup_teardown.py
airflow/sdk/definitions/_internal/templater.py
apache_airflow_task_sdk-1.1.7rc1.dist-info/METADATA
apache_airflow_task_sdk-1.1.7rc1.dist-info/WHEEL
apache_airflow_task_sdk-1.1.7rc1.dist-info/licenses/LICENSE
apache_airflow_task_sdk-1.1.7rc1.dist-info/licenses/NOTICE
apache_airflow_task_sdk-1.1.7rc1.dist-info/RECORD
