Metadata-Version: 2.4
Name: apache-airflow-task-sdk
Version: 1.1.7rc1
Summary: Python Task SDK for Apache Airflow DAG Authors
Project-URL: Bug Tracker, https://github.com/apache/airflow/issues
Project-URL: Documentation, https://airflow.staged.apache.org/docs/
Project-URL: Homepage, https://airflow.staged.apache.org/
Project-URL: Slack Chat, https://s.apache.org/airflow-slack
Project-URL: Source Code, https://github.com/apache/airflow
Project-URL: Mastodon, https://fosstodon.org/@airflow
Project-URL: Bluesky, https://bsky.app/profile/apache-airflow.bsky.social
Project-URL: YouTube, https://www.youtube.com/channel/UCSXwxpWZQ7XZ1WL3wqevChA/
Author-email: Apache Software Foundation <dev@airflow.apache.org>
Maintainer-email: Apache Software Foundation <dev@airflow.apache.org>
License-Expression: Apache-2.0
License-File: LICENSE
License-File: NOTICE
Keywords: airflow,automation,dag,data,orchestration,pipelines,workflow
Classifier: Development Status :: 5 - Production/Stable
Classifier: Environment :: Console
Classifier: Environment :: Web Environment
Classifier: Framework :: Apache Airflow
Classifier: Intended Audience :: Developers
Classifier: Intended Audience :: System Administrators
Classifier: Programming Language :: Python :: 3.10
Classifier: Programming Language :: Python :: 3.11
Classifier: Programming Language :: Python :: 3.12
Classifier: Programming Language :: Python :: 3.13
Classifier: Topic :: System :: Monitoring
Requires-Python: <3.14,>=3.10
Requires-Dist: apache-airflow-core<3.2.0,>=3.1.7rc1
Requires-Dist: asgiref>=2.3.0
Requires-Dist: attrs!=25.2.0,>=24.2.0
Requires-Dist: babel>=2.17.0
Requires-Dist: colorlog>=6.8.2
Requires-Dist: fsspec>=2023.10.0
Requires-Dist: greenback>=1.2.1
Requires-Dist: httpx>=0.27.0
Requires-Dist: jinja2>=3.1.5
Requires-Dist: methodtools>=0.4.7
Requires-Dist: msgspec>=0.19.0
Requires-Dist: pendulum>=3.1.0
Requires-Dist: psutil>=6.1.0
Requires-Dist: pydantic>2.11.0
Requires-Dist: pygtrie>=2.5.0
Requires-Dist: python-dateutil>=2.7.0
Requires-Dist: structlog>=25.4.0
Requires-Dist: tenacity>=8.3.0
